properties_inheritance_graph/__init__.py
properties_inheritance_graph/graph.py
properties_inheritance_graph-1.0.0.dist-info/METADATA
properties_inheritance_graph-1.0.0.dist-info/WHEEL
properties_inheritance_graph-1.0.0.dist-info/top_level.txt
properties_inheritance_graph-1.0.0.dist-info/RECORD
