Metadata-Version: 2.1
Name: properties-inheritance-graph
Version: 1.0.0
Summary: Make graphs of HasProperties class networks
Home-page: https://github.com/seequent/properties-inheritance-graph
Author: Seequent
Author-email: franklin.koch@seequent.com
License: UNKNOWN
Keywords: networkx,properties,graph
Platform: Windows
Platform: Linux
Platform: Solaris
Platform: Mac OS-X
Platform: Unix
Classifier: Development Status :: 4 - Beta
Classifier: Programming Language :: Python
Classifier: Topic :: Scientific/Engineering
Classifier: Topic :: Scientific/Engineering :: Mathematics
Classifier: Topic :: Scientific/Engineering :: Physics
Classifier: Operating System :: Microsoft :: Windows
Classifier: Operating System :: POSIX
Classifier: Operating System :: Unix
Classifier: Operating System :: MacOS
Classifier: Natural Language :: English
Requires-Dist: properties
Requires-Dist: networkx
